{
  "project_info": {
    "project_number": "605376329919",
    "project_id": "flutter-chat-app-ac88b",
    "storage_bucket": "flutter-chat-app-ac88b.appspot.com"
  },
  "client": [
    {
      "client_info": {
        "mobilesdk_app_id": "1:605376329919:android:1aaab6f2dbed19cc4e6e0a",
        "android_client_info": {
          "package_name": "com.example.chat_app"
        }
      },
      "oauth_client": [],
      "api_key": [
        {
          "current_key": "AIzaSyBmT6X3KmQkYaw7HeRD8odb-_gww3bNKbY"
        }
      ],
      "services": {
        "appinvite_service": {
          "other_platform_oauth_client": []
        }
      }
    }
  ],
  "configuration_version": "1"
}